{
	"beta": {
		"version_name": "5.7 (Update 13)",
		"version_code": "583",
		"min_version_code": "582",
		"content": "<b>Версия 5.8 (Update 13) - Release</b><br/><a href=\"https://apk.anilabx.xyz/anilabx-latest-beta.apk\">Скачать файл через браузер</a><br><br><a href=\"https://anilabx.xyz/ru/installation/changelog.html\">Список изменений на официальном сайте</a>"
	},
	"release": {
		"version_name": "5.7 (Update 13)",
		"version_code": "583",
		"min_version_code": "582",
		"content": "<b>Версия 5.7 (Update 13) - Release</b><br/><a href=\"https://apk.anilabx.xyz/anilabx-latest.apk\">Скачать файл через браузер</a><br><br><a href=\"https://anilabx.xyz/ru/installation/changelog.html\">Список изменений на официальном сайте</a>"
	}
}
